setup.cfg
setup.py
belashovplot/__init__.py
belashovplot/belashovplot.py
belashovplot.egg-info/PKG-INFO
belashovplot.egg-info/SOURCES.txt
belashovplot.egg-info/dependency_links.txt
belashovplot.egg-info/not-zip-safe
belashovplot.egg-info/top_level.txt