Metadata-Version: 2.1
Name: belashovplot
Version: 1.0
Summary: High level library to construct graphics with matplotlib
Home-page: UNKNOWN
Author-email: Uclaptrap@gmail.com
License: UNKNOWN
Platform: UNKNOWN
